cheap_settings/__init__.py
cheap_settings/__init__.pyi
cheap_settings/cheap_settings.py
cheap_settings/command_line.py
cheap_settings/py.typed
cheap_settings-1.4.0.dist-info/METADATA
cheap_settings-1.4.0.dist-info/WHEEL
cheap_settings-1.4.0.dist-info/licenses/LICENSE
cheap_settings-1.4.0.dist-info/RECORD
