Metadata-Version: 2.4
Name: cheap-settings
Version: 1.4.0
Summary: A lightweight, low footprint settings system
Project-URL: homepage, https://github.com/evanjpw/cheap-settings
Project-URL: repository, https://github.com/evanjpw/cheap-settings
Project-URL: documentation, https://evanjpw.github.io/cheap-settings/
Project-URL: issues, https://github.com/evanjpw/cheap-settings/issues
Project-URL: changelog, https://github.com/evanjpw/cheap-settings/blob/master/CHANGELOG.md
Author-email: Evan Williams <evanjpw@gmail.com>
License-Expression: MIT
License-File: LICENSE
Keywords: application,config,configuration,configurations,env,environment,environments,python,python-config,settings
Classifier: Development Status :: 5 - Production/Stable
Classifier: Intended Audience :: Developers
Classifier: License :: OSI Approved :: MIT License
Classifier: Programming Language :: Python :: 3 :: Only
Classifier: Programming Language :: Python :: 3.8
Classifier: Programming Language :: Python :: 3.9
Classifier: Programming Language :: Python :: 3.10
Classifier: Programming Language :: Python :: 3.11
Classifier: Programming Language :: Python :: 3.12
Classifier: Programming Language :: Python :: 3.13
Classifier: Topic :: Software Development :: Libraries
Requires-Python: >=3.8
Provides-Extra: dev
Requires-Dist: isort>=5.13.2; extra == 'dev'
Requires-Dist: mkdocs-material>=9.6.21; extra == 'dev'
Requires-Dist: mkdocs>=1.6.1; extra == 'dev'
Requires-Dist: mkdocstrings[python]>=0.11.4; extra == 'dev'
Requires-Dist: pre-commit>=3.5.0; extra == 'dev'
Requires-Dist: pytest-cov>=5.0.0; extra == 'dev'
Requires-Dist: pytest>=7.0.0; extra == 'dev'
Requires-Dist: ruff>=0.13.3; extra == 'dev'
